metatemplating/Template.py
metatemplating/__init__.py
metatemplating-1.0.2.dist-info/LICENSE
metatemplating-1.0.2.dist-info/METADATA
metatemplating-1.0.2.dist-info/WHEEL
metatemplating-1.0.2.dist-info/top_level.txt
metatemplating-1.0.2.dist-info/RECORD
